liepack/__init__.py
liepack/liepack.py
liepack/release.py
liepack/domain/__init__.py
liepack/domain/hspaces/__init__.py
liepack/domain/hspaces/hspaces.py
liepack/domain/liealgebras/__init__.py
liepack/domain/liealgebras/liealgebras.py
liepack/domain/liealgebras/tests/test_liealgebras.py
liepack/domain/liegroups/__init__.py
liepack/domain/liegroups/liegroups.py
liepack/domain/liegroups/tests/test_liegroups.py
liepack/field/__init__.py
liepack/field/vectorfield.py
liepack/flow/__init__.py
liepack/flow/flow.py
liepack/flow/timesteppers.py
liepack/flow/methods/RK.csv
liepack/tests/test_liepack.py
liepack-0.1.1.dist-info/LICENSE
liepack-0.1.1.dist-info/METADATA
liepack-0.1.1.dist-info/WHEEL
liepack-0.1.1.dist-info/top_level.txt
liepack-0.1.1.dist-info/RECORD
